Metadata-Version: 2.4
Name: invoicing-pdf-convert
Version: 1.0.0
Summary: This package can be used to convert Excel invoices to PDF invoices.
Home-page: https://github.com/juanma-codes/invoicing
Author: Manuel Martinez
Author-email: manuelmartinez199802@gmail.com
License: MIT
Keywords: invoice,excel,pdf
Classifier: Development Status :: 3 - Alpha
Classifier: Intended Audience :: Developers
Classifier: Topic :: Software Development :: Build Tools
Classifier: License :: OSI Approved :: MIT License
Classifier: Programming Language :: Python :: 3.8
Classifier: Programming Language :: Python :: 3.9
Classifier: Programming Language :: Python :: 3.10
Classifier: Programming Language :: Python :: 3.11
Requires-Dist: fpdf
Requires-Dist: openpyxl
Requires-Dist: pandas
Dynamic: author
Dynamic: author-email
Dynamic: classifier
Dynamic: home-page
Dynamic: keywords
Dynamic: license
Dynamic: requires-dist
Dynamic: summary
